{
  "best-products": [
    {
      "id": 1,
      "kode": "k-1",
      "nama": "Lenovo y",
      "harga": 12000000,
      "is_ready": true,
      "gambar": "lenovo.png"
    },
    {
      "id": 2,
      "kode": "k-2",
      "nama": "Iphone x",
      "harga": 13000000,
      "is_ready": true,
      "gambar": "iphonex.jpg"
    },
    {
      "id": 3,
      "kode": "k-3",
      "nama": "Asus ROG",
      "harga": 30000000,
      "is_ready": true,
      "gambar": "iphonex.jpg"
    },
    {
      "id": 4,
      "kode": "k-4",
      "nama": "Lenovo y",
      "harga": 12000000,
      "is_ready": true,
      "gambar": "lenovo.png"
    }
  ],
  "products": [
    {
      "id": 1,
      "kode": "k-1",
      "nama": "Lenovo y",
      "harga": 12000000,
      "is_ready": true,
      "gambar": "lenovo.png"
    },
    {
      "id": 2,
      "kode": "k-2",
      "nama": "Iphone x",
      "harga": 12000000,
      "is_ready": true,
      "gambar": "iphonex.jpg"
    },
    {
      "id": 3,
      "kode": "k-3",
      "nama": "Lenovo y",
      "harga": 12000000,
      "is_ready": true,
      "gambar": "lenovo.png"
    },
    {
      "id": 4,
      "kode": "k-4",
      "nama": "Lenovo y",
      "harga": 12000000,
      "is_ready": true,
      "gambar": "lenovo.png"
    },
    {
      "id": 5,
      "kode": "k-5",
      "nama": "Lenovo y",
      "harga": 12000000,
      "is_ready": true,
      "gambar": "lenovo.png"
    },
    {
      "id": 6,
      "kode": "k-6",
      "nama": "Lenovo y",
      "harga": 12000000,
      "is_ready": true,
      "gambar": "lenovo.png"
    }
  ],
  "keranjang": [
    {
      "jumlah_pesanan": "1",
      "keterangan": "dd",
      "product": {
        "id": 3,
        "kode": "k-3",
        "nama": "Lenovo y",
        "harga": 12000000,
        "is_ready": true,
        "gambar": "lenovo.png"
      },
      "id": 1
    },
    {
      "jumlah_pesanan": "2",
      "keterangan": "dsf",
      "product": {
        "id": 2,
        "kode": "k-2",
        "nama": "Iphone x",
        "harga": 12000000,
        "is_ready": true,
        "gambar": "iphonex.jpg"
      },
      "id": 2
    },
    {
      "jumlah_pesanan": "3",
      "keterangan": "erwe",
      "product": {
        "id": 3,
        "kode": "k-3",
        "nama": "Lenovo y",
        "harga": 12000000,
        "is_ready": true,
        "gambar": "lenovo.png"
      },
      "id": 3
    },
    {
      "jumlah_pesanan": "7",
      "keterangan": "fdsg",
      "product": {
        "id": 2,
        "kode": "k-2",
        "nama": "Iphone x",
        "harga": 12000000,
        "is_ready": true,
        "gambar": "iphonex.jpg"
      },
      "id": 4
    }
  ],
  "profile": {
    "name": "typicode"
  }
}